app/__init__.py
app/api/controllers/__init__.py
app/api/controllers/add_task/__init__.py
app/api/controllers/add_task/controller.py
app/api/controllers/add_task/responses.py
app/api/controllers/add_task/router.py
app/api/controllers/delete_task/__init__.py
app/api/controllers/delete_task/controller.py
app/api/controllers/delete_task/responses.py
app/api/controllers/delete_task/router.py
app/api/controllers/get_task/__init__.py
app/api/controllers/get_task/controller.py
app/api/controllers/get_task/responses.py
app/api/controllers/get_task/router.py
app/api/controllers/update_task/__init__.py
app/api/controllers/update_task/controller.py
app/api/controllers/update_task/responses.py
app/api/controllers/update_task/router.py
app/api/dependencies.py
app/api/exceptions/__init__.py
app/api/exceptions/failed_to_decode.py
app/api/exceptions/invalid_token.py
app/api/exceptions/not_authenticated.py
app/api/exceptions/task_not_found.py
app/api/exceptions/wrong_mime_type.py
app/api/router.py
app/config/auth.py
app/config/database.py
app/config/network.py
app/database/base_model.py
app/database/client.py
app/database/models/__init__.py
app/database/models/face.py
app/database/models/image.py
app/database/models/task.py
app/database/types.py
app/main.py
app/network/client.py
app/serialization/base_schema.py
app/serialization/schemas/__init__.py
app/serialization/schemas/face.py
app/serialization/schemas/image.py
app/serialization/schemas/task.py
app/serialization/types.py
app/use_cases/database/__init__.py
app/use_cases/database/delete_task.py
app/use_cases/database/read_task.py
app/use_cases/database/task_exist.py
app/use_cases/database/write_image.py
app/use_cases/database/write_task.py
app/use_cases/file_system/__init__.py
app/use_cases/file_system/delete_file.py
app/use_cases/file_system/write_file.py
app/use_cases/network/__init__.py
app/use_cases/network/recognize_photo.py
app/use_cases/utils/__init__.py
app/use_cases/utils/file_gen.py
app/use_cases/utils/security.py
human_recognition_app-0.1.0.dist-info/LICENSE
human_recognition_app-0.1.0.dist-info/METADATA
human_recognition_app-0.1.0.dist-info/WHEEL
human_recognition_app-0.1.0.dist-info/RECORD
