Metadata-Version: 2.1
Name: human-recognition-app
Version: 0.1.0
Summary: App for face recognition in photo.
Author: bobunist
Author-email: 92374148+bobunist@users.noreply.github.com
Requires-Python: >=3.12,<4.0
Classifier: Programming Language :: Python :: 3
Classifier: Programming Language :: Python :: 3.12
Requires-Dist: aiofile (>=3.8.8,<4.0.0)
Requires-Dist: aiohttp[speedups] (>=3.10.5,<4.0.0)
Requires-Dist: alembic (>=1.13.2,<2.0.0)
Requires-Dist: asyncpg (>=0.29.0,<0.30.0)
Requires-Dist: fastapi (>=0.114.0,<0.115.0)
Requires-Dist: gunicorn (>=23.0.0,<24.0.0)
Requires-Dist: httptools (>=0.6.1,<0.7.0)
Requires-Dist: orjson (>=3.10.7,<4.0.0)
Requires-Dist: pydantic-settings (>=2.4.0,<3.0.0)
Requires-Dist: python-dotenv (>=1.0.1,<2.0.0)
Requires-Dist: python-multipart (>=0.0.9,<0.0.10)
Requires-Dist: singleton-package (>=0.6.0,<0.7.0)
Requires-Dist: sqlalchemy (>=2.0.34,<3.0.0)
Requires-Dist: tzdata (>=2024.1,<2025.0)
Requires-Dist: uvicorn (>=0.30.6,<0.31.0)
Requires-Dist: uvloop (>=0.20.0,<0.21.0) ; sys_platform == "linux"
